simpletaskrun/__init__.py
simpletaskrun-0.0.3.dist-info/LICENSE
simpletaskrun-0.0.3.dist-info/METADATA
simpletaskrun-0.0.3.dist-info/WHEEL
simpletaskrun-0.0.3.dist-info/top_level.txt
simpletaskrun-0.0.3.dist-info/RECORD
