Metadata-Version: 2.1
Name: simpletaskrun
Version: 0.0.3
Summary: Parallel function excutor interface
Home-page: 
Author: 
Author-email: 
Classifier: Programming Language :: Python :: 3
Classifier: License :: OSI Approved :: MIT License
Classifier: Operating System :: OS Independent
Requires-Python: >=3
License-File: LICENSE
Requires-Dist: termcolor
